deephyp/__init__.py
deephyp/autoencoder.py
deephyp/classifier.py
deephyp/data.py
deephyp/network_ops.py
deephyp-0.1.5.dist-info/LICENSE
deephyp-0.1.5.dist-info/METADATA
deephyp-0.1.5.dist-info/WHEEL
deephyp-0.1.5.dist-info/top_level.txt
deephyp-0.1.5.dist-info/RECORD
