Metadata-Version: 2.1
Name: deephyp
Version: 0.1.5
Summary: Tools for training and using unsupervised autoencoders and supervised deep learning classifiers for hyperspectral data.
Home-page: https://deephyp.readthedocs.io/en/latest/index.html
Author: Lloyd Windrim
Author-email: lloydwindrim@gmail.com
License: MIT
Platform: UNKNOWN
Classifier: License :: OSI Approved :: MIT License
Classifier: Programming Language :: Python
Classifier: Programming Language :: Python :: 2
Classifier: Programming Language :: Python :: 3
Requires-Dist: numpy
